lazy_object_proxy/_version.py
lazy_object_proxy/__init__.py
lazy_object_proxy/cext.cpython-38-x86_64-linux-gnu.so
lazy_object_proxy/simple.py
lazy_object_proxy/utils.py
lazy_object_proxy/compat.py
lazy_object_proxy/slots.py
lazy_object_proxy-1.9.0.dist-info/AUTHORS.rst
lazy_object_proxy-1.9.0.dist-info/RECORD
lazy_object_proxy-1.9.0.dist-info/METADATA
lazy_object_proxy-1.9.0.dist-info/top_level.txt
lazy_object_proxy-1.9.0.dist-info/LICENSE
lazy_object_proxy-1.9.0.dist-info/WHEEL
