Metadata-Version: 2.1
Name: lazy-object-proxy
Version: 1.9.0
Summary: A fast and thorough lazy object proxy.
Home-page: https://github.com/ionelmc/python-lazy-object-proxy
Author: Ionel Cristian Mărieș
Author-email: contact@ionelmc.ro
License: BSD-2-Clause
Project-URL: Documentation, https://python-lazy-object-proxy.readthedocs.io/
Project-URL: Changelog, https://python-lazy-object-proxy.readthedocs.io/en/latest/changelog.html
Project-URL: Issue Tracker, https://github.com/ionelmc/python-lazy-object-proxy/issues
Platform: UNKNOWN
Classifier: Development Status :: 5 - Production/Stable
Classifier: Intended Audience :: Developers
Classifier: License :: OSI Approved :: BSD License
Classifier: Operating System :: Unix
Classifier: Operating System :: POSIX
Classifier: Operating System :: Microsoft :: Windows
Classifier: Programming Language :: Python
Classifier: Programming Language :: Python :: 3
Classifier: Programming Language :: Python :: 3 :: Only
Classifier: Programming Language :: Python :: 3.7
Classifier: Programming Language :: Python :: 3.8
Classifier: Programming Language :: Python :: 3.9
Classifier: Programming Language :: Python :: 3.10
Classifier: Programming Language :: Python :: 3.11
Classifier: Programming Language :: Python :: Implementation :: CPython
Classifier: Programming Language :: Python :: Implementation :: PyPy
Classifier: Topic :: Utilities
Requires-Python: >=3.7
License-File: LICENSE
License-File: AUTHORS.rst
